AWSGlueInteractiveSessionsKernel-0.4.data/data/aws_lambda/handlers.py
AWSGlueInteractiveSessionsKernel-0.4.data/data/aws_lambda/lambda-transform.yml
aws_glue_interactive_sessions_kernel/__init__.py
aws_glue_interactive_sessions_kernel/glue_kernel.py
aws_glue_interactive_sessions_kernel/install.sh
aws_glue_interactive_sessions_kernel/service-2.json
aws_glue_interactive_sessions_kernel/glue_python_kernel/GlueKernel.py
aws_glue_interactive_sessions_kernel/glue_python_kernel/KernelMagics.py
aws_glue_interactive_sessions_kernel/glue_python_kernel/__init__.py
aws_glue_interactive_sessions_kernel/glue_python_kernel/constants.py
aws_glue_interactive_sessions_kernel/glue_python_kernel/kernel.json
aws_glue_interactive_sessions_kernel/glue_python_kernel/test.py
aws_glue_interactive_sessions_kernel/glue_scala_kernel/GlueKernel.py
aws_glue_interactive_sessions_kernel/glue_scala_kernel/KernelMagics.py
aws_glue_interactive_sessions_kernel/glue_scala_kernel/__init__.py
aws_glue_interactive_sessions_kernel/glue_scala_kernel/constants.py
aws_glue_interactive_sessions_kernel/glue_scala_kernel/kernel.json
python3.6/site-packages/AWSGlueInteractiveSessionsKernel-0.1-py3.6.egg-info/PKG-INFO
python3.6/site-packages/AWSGlueInteractiveSessionsKernel-0.1-py3.6.egg-info/SOURCES.txt
python3.6/site-packages/AWSGlueInteractiveSessionsKernel-0.1-py3.6.egg-info/dependency_links.txt
python3.6/site-packages/AWSGlueInteractiveSessionsKernel-0.1-py3.6.egg-info/entry_points.txt
python3.6/site-packages/AWSGlueInteractiveSessionsKernel-0.1-py3.6.egg-info/requires.txt
python3.6/site-packages/AWSGlueInteractiveSessionsKernel-0.1-py3.6.egg-info/top_level.txt
python3.6/site-packages/AWSGlueInteractiveSessionsKernel-0.3-py3.6.egg-info/PKG-INFO
python3.6/site-packages/AWSGlueInteractiveSessionsKernel-0.3-py3.6.egg-info/SOURCES.txt
python3.6/site-packages/AWSGlueInteractiveSessionsKernel-0.3-py3.6.egg-info/dependency_links.txt
python3.6/site-packages/AWSGlueInteractiveSessionsKernel-0.3-py3.6.egg-info/entry_points.txt
python3.6/site-packages/AWSGlueInteractiveSessionsKernel-0.3-py3.6.egg-info/requires.txt
python3.6/site-packages/AWSGlueInteractiveSessionsKernel-0.3-py3.6.egg-info/top_level.txt
python3.6/site-packages/AWSGlueInteractiveSessionsKernel-1.0-py3.6.egg-info/PKG-INFO
python3.6/site-packages/AWSGlueInteractiveSessionsKernel-1.0-py3.6.egg-info/SOURCES.txt
python3.6/site-packages/AWSGlueInteractiveSessionsKernel-1.0-py3.6.egg-info/dependency_links.txt
python3.6/site-packages/AWSGlueInteractiveSessionsKernel-1.0-py3.6.egg-info/entry_points.txt
python3.6/site-packages/AWSGlueInteractiveSessionsKernel-1.0-py3.6.egg-info/requires.txt
python3.6/site-packages/AWSGlueInteractiveSessionsKernel-1.0-py3.6.egg-info/top_level.txt
python3.6/site-packages/aws_glue_interactive_sessions_kernel/__init__.py
python3.6/site-packages/aws_glue_interactive_sessions_kernel/glue_kernel.py
python3.6/site-packages/aws_glue_interactive_sessions_kernel/install.sh
python3.6/site-packages/aws_glue_interactive_sessions_kernel/service-2.json
python3.6/site-packages/aws_glue_interactive_sessions_kernel/glue_python_kernel/GlueKernel.py
python3.6/site-packages/aws_glue_interactive_sessions_kernel/glue_python_kernel/KernelMagics.py
python3.6/site-packages/aws_glue_interactive_sessions_kernel/glue_python_kernel/__init__.py
python3.6/site-packages/aws_glue_interactive_sessions_kernel/glue_python_kernel/constants.py
python3.6/site-packages/aws_glue_interactive_sessions_kernel/glue_python_kernel/kernel.json
python3.6/site-packages/aws_glue_interactive_sessions_kernel/glue_scala_kernel/GlueKernel.py
python3.7/site-packages/AWSGlueInteractiveSessionsKernel-0.1-py3.7.egg-info/PKG-INFO
python3.7/site-packages/AWSGlueInteractiveSessionsKernel-0.1-py3.7.egg-info/SOURCES.txt
python3.7/site-packages/AWSGlueInteractiveSessionsKernel-0.1-py3.7.egg-info/dependency_links.txt
python3.7/site-packages/AWSGlueInteractiveSessionsKernel-0.1-py3.7.egg-info/entry_points.txt
python3.7/site-packages/AWSGlueInteractiveSessionsKernel-0.1-py3.7.egg-info/requires.txt
python3.7/site-packages/AWSGlueInteractiveSessionsKernel-0.1-py3.7.egg-info/top_level.txt
python3.7/site-packages/AWSGlueInteractiveSessionsKernel-0.3-py3.7.egg-info/PKG-INFO
python3.7/site-packages/AWSGlueInteractiveSessionsKernel-0.3-py3.7.egg-info/SOURCES.txt
python3.7/site-packages/AWSGlueInteractiveSessionsKernel-0.3-py3.7.egg-info/dependency_links.txt
python3.7/site-packages/AWSGlueInteractiveSessionsKernel-0.3-py3.7.egg-info/entry_points.txt
python3.7/site-packages/AWSGlueInteractiveSessionsKernel-0.3-py3.7.egg-info/requires.txt
python3.7/site-packages/AWSGlueInteractiveSessionsKernel-0.3-py3.7.egg-info/top_level.txt
python3.7/site-packages/AWSGlueInteractiveSessionsKernel-1.0-py3.7.egg-info/PKG-INFO
python3.7/site-packages/AWSGlueInteractiveSessionsKernel-1.0-py3.7.egg-info/SOURCES.txt
python3.7/site-packages/AWSGlueInteractiveSessionsKernel-1.0-py3.7.egg-info/dependency_links.txt
python3.7/site-packages/AWSGlueInteractiveSessionsKernel-1.0-py3.7.egg-info/entry_points.txt
python3.7/site-packages/AWSGlueInteractiveSessionsKernel-1.0-py3.7.egg-info/requires.txt
python3.7/site-packages/AWSGlueInteractiveSessionsKernel-1.0-py3.7.egg-info/top_level.txt
AWSGlueInteractiveSessionsKernel-0.4.dist-info/METADATA
AWSGlueInteractiveSessionsKernel-0.4.dist-info/WHEEL
AWSGlueInteractiveSessionsKernel-0.4.dist-info/entry_points.txt
AWSGlueInteractiveSessionsKernel-0.4.dist-info/top_level.txt
AWSGlueInteractiveSessionsKernel-0.4.dist-info/RECORD
